datalab_kernel/__init__.py
datalab_kernel/__main__.py
datalab_kernel/discovery.py
datalab_kernel/install.py
datalab_kernel/kernel.py
datalab_kernel/plotter.py
datalab_kernel/serialization_npz.py
datalab_kernel/startup.py
datalab_kernel/workspace.py
datalab_kernel/backends/__init__.py
datalab_kernel/backends/pyfetch.py
datalab_kernel/backends/standalone.py
datalab_kernel/backends/webapi.py
datalab_kernel/tests/__init__.py
datalab_kernel/tests/benchmark_image_transfer.py
datalab_kernel/tests/conftest.py
datalab_kernel/tests/data.py
datalab_kernel/tests/test_webapi_backend.py
datalab_kernel/tests/contract/__init__.py
datalab_kernel/tests/contract/test_api.py
datalab_kernel/tests/integration/__init__.py
datalab_kernel/tests/integration/test_live_backend.py
datalab_kernel/tests/unit/__init__.py
datalab_kernel/tests/unit/test_install.py
datalab_kernel/tests/unit/test_kernel.py
datalab_kernel/tests/unit/test_objects.py
datalab_kernel/tests/unit/test_persistence.py
datalab_kernel/tests/unit/test_plotter.py
datalab_kernel/tests/unit/test_workspace.py
datalab_kernel-0.2.8.dist-info/licenses/LICENSE
datalab_kernel-0.2.8.dist-info/METADATA
datalab_kernel-0.2.8.dist-info/WHEEL
datalab_kernel-0.2.8.dist-info/entry_points.txt
datalab_kernel-0.2.8.dist-info/top_level.txt
datalab_kernel-0.2.8.dist-info/RECORD
