Metadata-Version: 2.4
Name: datalab-kernel
Version: 0.2.8
Summary: A standalone Xeus-Python-based Jupyter kernel for DataLab with optional live synchronization
Author-email: DataLab Platform Developers <p.raybaut@codra.fr>
License: BSD-3-Clause
Project-URL: Homepage, https://github.com/DataLab-Platform/DataLab-Kernel
Project-URL: Documentation, https://datalab-kernel.readthedocs.io/
Project-URL: Repository, https://github.com/DataLab-Platform/DataLab-Kernel.git
Project-URL: Issues, https://github.com/DataLab-Platform/DataLab-Kernel/issues
Keywords: jupyter,kernel,datalab,scientific,data processing,xeus
Classifier: Development Status :: 3 - Alpha
Classifier: Framework :: Jupyter
Classifier: Intended Audience :: Science/Research
Classifier: License :: OSI Approved :: BSD License
Classifier: Operating System :: OS Independent
Classifier: Programming Language :: Python :: 3
Classifier: Programming Language :: Python :: 3.9
Classifier: Programming Language :: Python :: 3.10
Classifier: Programming Language :: Python :: 3.11
Classifier: Programming Language :: Python :: 3.12
Classifier: Topic :: Scientific/Engineering
Requires-Python: >=3.9
License-File: LICENSE
Requires-Dist: xeus-python>=0.17.0
Requires-Dist: xeus-python-shell>=0.6.0
Requires-Dist: numpy>=1.22
Requires-Dist: httpx>=0.25.0
Requires-Dist: h5py>=3.0
Requires-Dist: matplotlib>=3.5
Requires-Dist: sigima>=1.0
Provides-Extra: cli
Requires-Dist: jupyter-client>=7.0; extra == "cli"
Provides-Extra: dev
Requires-Dist: pytest>=7.0; extra == "dev"
Requires-Dist: pytest-cov>=4.0; extra == "dev"
Requires-Dist: ruff>=0.1.0; extra == "dev"
Provides-Extra: doc
Requires-Dist: sphinx>=7.0; extra == "doc"
Requires-Dist: pydata-sphinx-theme>=0.14; extra == "doc"
Requires-Dist: myst-nb>=1.0; extra == "doc"
Requires-Dist: sphinx-design>=0.5; extra == "doc"
Requires-Dist: sphinx-copybutton>=0.5; extra == "doc"
Provides-Extra: datalab
Requires-Dist: datalab-platform>=1.1; extra == "datalab"
Dynamic: license-file
